foldingathome/__init__.py
foldingathome/donor.py
foldingathome/monthly.py
foldingathome/team.py
foldingathome-0.2.0.dist-info/LICENSE
foldingathome-0.2.0.dist-info/METADATA
foldingathome-0.2.0.dist-info/WHEEL
foldingathome-0.2.0.dist-info/top_level.txt
foldingathome-0.2.0.dist-info/RECORD
